odoo/addons/stock_warehouse_flow/README.rst
odoo/addons/stock_warehouse_flow/__init__.py
odoo/addons/stock_warehouse_flow/__manifest__.py
odoo/addons/stock_warehouse_flow/demo/stock_warehouse_flow.xml
odoo/addons/stock_warehouse_flow/i18n/es.po
odoo/addons/stock_warehouse_flow/i18n/it.po
odoo/addons/stock_warehouse_flow/i18n/stock_warehouse_flow.pot
odoo/addons/stock_warehouse_flow/models/__init__.py
odoo/addons/stock_warehouse_flow/models/delivery_carrier.py
odoo/addons/stock_warehouse_flow/models/stock_move.py
odoo/addons/stock_warehouse_flow/models/stock_route.py
odoo/addons/stock_warehouse_flow/models/stock_warehouse.py
odoo/addons/stock_warehouse_flow/models/stock_warehouse_flow.py
odoo/addons/stock_warehouse_flow/readme/CONFIGURE.md
odoo/addons/stock_warehouse_flow/readme/CONTRIBUTORS.md
odoo/addons/stock_warehouse_flow/readme/DESCRIPTION.md
odoo/addons/stock_warehouse_flow/readme/ROADMAP.md
odoo/addons/stock_warehouse_flow/readme/USAGE.md
odoo/addons/stock_warehouse_flow/security/ir.model.access.csv
odoo/addons/stock_warehouse_flow/static/description/config.png
odoo/addons/stock_warehouse_flow/static/description/flow.png
odoo/addons/stock_warehouse_flow/static/description/icon.png
odoo/addons/stock_warehouse_flow/static/description/index.html
odoo/addons/stock_warehouse_flow/tests/__init__.py
odoo/addons/stock_warehouse_flow/tests/common.py
odoo/addons/stock_warehouse_flow/tests/test_delivery_carrier.py
odoo/addons/stock_warehouse_flow/tests/test_warehouse.py
odoo/addons/stock_warehouse_flow/tests/test_warehouse_flow.py
odoo/addons/stock_warehouse_flow/views/delivery_carrier.xml
odoo/addons/stock_warehouse_flow/views/stock_route.xml
odoo/addons/stock_warehouse_flow/views/stock_warehouse.xml
odoo/addons/stock_warehouse_flow/views/stock_warehouse_flow.xml
odoo_addon_stock_warehouse_flow-17.0.1.0.0.3.dist-info/METADATA
odoo_addon_stock_warehouse_flow-17.0.1.0.0.3.dist-info/WHEEL
odoo_addon_stock_warehouse_flow-17.0.1.0.0.3.dist-info/top_level.txt
odoo_addon_stock_warehouse_flow-17.0.1.0.0.3.dist-info/RECORD
